{"resolution": 12, "max_bar": 8, "max_track_num": 12, "max_time_shift": 48, "program_instrument_map": {"0": "grand-piano", "1": "bright-piano", "2": "electric-grand-piano", "3": "honky-tony-piano", "4": "electric-piano-1", "5": "electric-piano-2", "6": "harpsichord", "7": "clavinet", "8": "celesta", "9": "glockenspiel", "10": "music-box", "11": "vibraphone", "12": "marimba", "13": "xylophone", "14": "tubular-bells", "15": "dulcimer", "16": "dwawbar-organ", "17": "percussive-organ", "18": "rock-organ", "19": "church-organ", "20": "reed-organ", "21": "accordion", "22": "harmonica", "23": "bandoneon", "24": "nylon-string-guitar", "25": "steel-string-guitar", "26": "jazz-electric-guitar", "27": "clean-electric-guitar", "28": "muted-electric-guitar", "29": "overdriven-electric-guitar", "30": "distort-electric-guitar", "31": "guitar-harmonic", "32": "bass", "33": "finger-electric-bass", "34": "pick-electric-bass", "35": "fretless-electric-bass", "36": "slap-bass-1", "37": "slap-bass-2", "38": "synth-bass-1", "39": "synth-bass-2", "40": "violin", "41": "viola", "42": "cello", "43": "contrabass", "44": "tremelo-strings", "45": "pizzicato-strings", "46": "harp", "47": "timpani", "48": "strings", "49": "strings", "50": "synth-strings-1", "51": "synth-strings-2", "52": "voices-aah", "53": "voices-ooh", "54": "synth-voice", "55": "orchestra-hit", "56": "trumpet", "57": "trombone", "58": "tuba", "59": "muted-trumpet", "60": "horn", "61": "brasses", "62": "synth-brasses-1", "63": "synth-brasses-2", "64": "soprano-saxophone", "65": "alto-saxophone", "66": "tenor-saxophone", "67": "baritone-saxophone", "68": "oboe", "69": "english-horn", "70": "bassoon", "71": "clarinet", "72": "piccolo", "73": "flute", "74": "recorder", "75": "pan-flute", "76": "blown-bottle", "77": "Shakuhachi", "78": "Whistle", "79": "ocarina", "80": "lead-square", "81": "lead-sawtooth", "82": "lead-calliope", "83": "lead-chiff", "84": "lead-charang", "85": "lead-voice", "86": "lead-fifths", "87": "lead-bass+lead", "88": "pad-new-age", "89": "pad-warm", "90": "pad-polysynth", "91": "pad-choir", "92": "pad-bowed", "93": "pad-metallic", "94": "pad-halo", "95": "pad-sweep", "96": "fx-rain", "97": "fx-soundtrack", "98": "fx-crystal", "99": "fx-atmosphere", "100": "fx-brightness", "101": "fx-goblins", "102": "fx-echoes", "103": "fx-scifi", "104": "sitar", "105": "banjo", "106": "shamisen", "107": "koto", "108": "kalimba", "109": "bag-pipe", "110": "violin", "111": "shehnai", "112": "tinkle-bell", "113": "agogo", "114": "steel-drum", "115": "woodblock", "116": "taiko", "117": "melodic-tom", "118": "synth-drums", "119": "reverse-cymbal", "120": "guitar-fret-noise", "121": "breath-noise", "122": "seashore", "123": "bird-tweet", "124": "telephone-rang", "125": "helicopter", "126": "applause", "127": "gunshot", "128": "drumset"}, "instrument_program_map": {"grand-piano": 0, "bright-piano": 1, "electric-grand-piano": 2, "honky-tony-piano": 3, "electric-piano-1": 4, "electric-piano-2": 5, "harpsichord": 6, "clavinet": 7, "celesta": 8, "glockenspiel": 9, "music-box": 10, "vibraphone": 11, "marimba": 12, "xylophone": 13, "tubular-bells": 14, "dulcimer": 15, "dwawbar-organ": 16, "percussive-organ": 17, "rock-organ": 18, "church-organ": 19, "reed-organ": 20, "accordion": 21, "harmonica": 22, "bandoneon": 23, "nylon-string-guitar": 24, "steel-string-guitar": 25, "jazz-electric-guitar": 26, "clean-electric-guitar": 27, "muted-electric-guitar": 28, "overdriven-electric-guitar": 29, "distort-electric-guitar": 30, "guitar-harmonic": 31, "bass": 32, "finger-electric-bass": 33, "pick-electric-bass": 34, "fretless-electric-bass": 35, "slap-bass-1": 36, "slap-bass-2": 37, "synth-bass-1": 38, "synth-bass-2": 39, "violin": 110, "viola": 41, "cello": 42, "contrabass": 43, "tremelo-strings": 44, "pizzicato-strings": 45, "harp": 46, "timpani": 47, "strings": 49, "synth-strings-1": 50, "synth-strings-2": 51, "voices-aah": 52, "voices-ooh": 53, "synth-voice": 54, "orchestra-hit": 55, "trumpet": 56, "trombone": 57, "tuba": 58, "muted-trumpet": 59, "horn": 60, "brasses": 61, "synth-brasses-1": 62, "synth-brasses-2": 63, "soprano-saxophone": 64, "alto-saxophone": 65, "tenor-saxophone": 66, "baritone-saxophone": 67, "oboe": 68, "english-horn": 69, "bassoon": 70, "clarinet": 71, "piccolo": 72, "flute": 73, "recorder": 74, "pan-flute": 75, "blown-bottle": 76, "Shakuhachi": 77, "Whistle": 78, "ocarina": 79, "lead-square": 80, "lead-sawtooth": 81, "lead-calliope": 82, "lead-chiff": 83, "lead-charang": 84, "lead-voice": 85, "lead-fifths": 86, "lead-bass+lead": 87, "pad-new-age": 88, "pad-warm": 89, "pad-polysynth": 90, "pad-choir": 91, "pad-bowed": 92, "pad-metallic": 93, "pad-halo": 94, "pad-sweep": 95, "fx-rain": 96, "fx-soundtrack": 97, "fx-crystal": 98, "fx-atmosphere": 99, "fx-brightness": 100, "fx-goblins": 101, "fx-echoes": 102, "fx-scifi": 103, "sitar": 104, "banjo": 105, "shamisen": 106, "koto": 107, "kalimba": 108, "bag-pipe": 109, "shehnai": 111, "tinkle-bell": 112, "agogo": 113, "steel-drum": 114, "woodblock": 115, "taiko": 116, "melodic-tom": 117, "synth-drums": 118, "reverse-cymbal": 119, "guitar-fret-noise": 120, "breath-noise": 121, "seashore": 122, "bird-tweet": 123, "telephone-rang": 124, "helicopter": 125, "applause": 126, "gunshot": 127, "drumset": 128}, "event_code_map": {"start-of-song": 0, "end-of-song": 1, "start-of-bar": 2, "end-of-bar": 3, "start-of-track": 4, "end-of-track": 5, "instrument_grand-piano": 6, "instrument_bright-piano": 7, "instrument_electric-grand-piano": 8, "instrument_honky-tony-piano": 9, "instrument_electric-piano-1": 10, "instrument_electric-piano-2": 11, "instrument_harpsichord": 12, "instrument_clavinet": 13, "instrument_celesta": 14, "instrument_glockenspiel": 15, "instrument_music-box": 16, "instrument_vibraphone": 17, "instrument_marimba": 18, "instrument_xylophone": 19, "instrument_tubular-bells": 20, "instrument_dulcimer": 21, "instrument_dwawbar-organ": 22, "instrument_percussive-organ": 23, "instrument_rock-organ": 24, "instrument_church-organ": 25, "instrument_reed-organ": 26, "instrument_accordion": 27, "instrument_harmonica": 28, "instrument_bandoneon": 29, "instrument_nylon-string-guitar": 30, "instrument_steel-string-guitar": 31, "instrument_jazz-electric-guitar": 32, "instrument_clean-electric-guitar": 33, "instrument_muted-electric-guitar": 34, "instrument_overdriven-electric-guitar": 35, "instrument_distort-electric-guitar": 36, "instrument_guitar-harmonic": 37, "instrument_bass": 38, "instrument_finger-electric-bass": 39, "instrument_pick-electric-bass": 40, "instrument_fretless-electric-bass": 41, "instrument_slap-bass-1": 42, "instrument_slap-bass-2": 43, "instrument_synth-bass-1": 44, "instrument_synth-bass-2": 45, "instrument_violin": 46, "instrument_viola": 47, "instrument_cello": 48, "instrument_contrabass": 49, "instrument_tremelo-strings": 50, "instrument_pizzicato-strings": 51, "instrument_harp": 52, "instrument_timpani": 53, "instrument_strings": 54, "instrument_synth-strings-1": 55, "instrument_synth-strings-2": 56, "instrument_voices-aah": 57, "instrument_voices-ooh": 58, "instrument_synth-voice": 59, "instrument_orchestra-hit": 60, "instrument_trumpet": 61, "instrument_trombone": 62, "instrument_tuba": 63, "instrument_muted-trumpet": 64, "instrument_horn": 65, "instrument_brasses": 66, "instrument_synth-brasses-1": 67, "instrument_synth-brasses-2": 68, "instrument_soprano-saxophone": 69, "instrument_alto-saxophone": 70, "instrument_tenor-saxophone": 71, "instrument_baritone-saxophone": 72, "instrument_oboe": 73, "instrument_english-horn": 74, "instrument_bassoon": 75, "instrument_clarinet": 76, "instrument_piccolo": 77, "instrument_flute": 78, "instrument_recorder": 79, "instrument_pan-flute": 80, "instrument_blown-bottle": 81, "instrument_Shakuhachi": 82, "instrument_Whistle": 83, "instrument_ocarina": 84, "instrument_lead-square": 85, "instrument_lead-sawtooth": 86, "instrument_lead-calliope": 87, "instrument_lead-chiff": 88, "instrument_lead-charang": 89, "instrument_lead-voice": 90, "instrument_lead-fifths": 91, "instrument_lead-bass+lead": 92, "instrument_pad-new-age": 93, "instrument_pad-warm": 94, "instrument_pad-polysynth": 95, "instrument_pad-choir": 96, "instrument_pad-bowed": 97, "instrument_pad-metallic": 98, "instrument_pad-halo": 99, "instrument_pad-sweep": 100, "instrument_fx-rain": 101, "instrument_fx-soundtrack": 102, "instrument_fx-crystal": 103, "instrument_fx-atmosphere": 104, "instrument_fx-brightness": 105, "instrument_fx-goblins": 106, "instrument_fx-echoes": 107, "instrument_fx-scifi": 108, "instrument_sitar": 109, "instrument_banjo": 110, "instrument_shamisen": 111, "instrument_koto": 112, "instrument_kalimba": 113, "instrument_bag-pipe": 114, "instrument_shehnai": 115, "instrument_tinkle-bell": 116, "instrument_agogo": 117, "instrument_steel-drum": 118, "instrument_woodblock": 119, "instrument_taiko": 120, "instrument_melodic-tom": 121, "instrument_synth-drums": 122, "instrument_reverse-cymbal": 123, "instrument_guitar-fret-noise": 124, "instrument_breath-noise": 125, "instrument_seashore": 126, "instrument_bird-tweet": 127, "instrument_telephone-rang": 128, "instrument_helicopter": 129, "instrument_applause": 130, "instrument_gunshot": 131, "instrument_drumset": 132, "note-on_0": 133, "note-on_1": 134, "note-on_2": 135, "note-on_3": 136, "note-on_4": 137, "note-on_5": 138, "note-on_6": 139, "note-on_7": 140, "note-on_8": 141, "note-on_9": 142, "note-on_10": 143, "note-on_11": 144, "note-on_12": 145, "note-on_13": 146, "note-on_14": 147, "note-on_15": 148, "note-on_16": 149, "note-on_17": 150, "note-on_18": 151, "note-on_19": 152, "note-on_20": 153, "note-on_21": 154, "note-on_22": 155, "note-on_23": 156, "note-on_24": 157, "note-on_25": 158, "note-on_26": 159, "note-on_27": 160, "note-on_28": 161, "note-on_29": 162, "note-on_30": 163, "note-on_31": 164, "note-on_32": 165, "note-on_33": 166, "note-on_34": 167, "note-on_35": 168, "note-on_36": 169, "note-on_37": 170, "note-on_38": 171, "note-on_39": 172, "note-on_40": 173, "note-on_41": 174, "note-on_42": 175, "note-on_43": 176, "note-on_44": 177, "note-on_45": 178, "note-on_46": 179, "note-on_47": 180, "note-on_48": 181, "note-on_49": 182, "note-on_50": 183, "note-on_51": 184, "note-on_52": 185, "note-on_53": 186, "note-on_54": 187, "note-on_55": 188, "note-on_56": 189, "note-on_57": 190, "note-on_58": 191, "note-on_59": 192, "note-on_60": 193, "note-on_61": 194, "note-on_62": 195, "note-on_63": 196, "note-on_64": 197, "note-on_65": 198, "note-on_66": 199, "note-on_67": 200, "note-on_68": 201, "note-on_69": 202, "note-on_70": 203, "note-on_71": 204, "note-on_72": 205, "note-on_73": 206, "note-on_74": 207, "note-on_75": 208, "note-on_76": 209, "note-on_77": 210, "note-on_78": 211, "note-on_79": 212, "note-on_80": 213, "note-on_81": 214, "note-on_82": 215, "note-on_83": 216, "note-on_84": 217, "note-on_85": 218, "note-on_86": 219, "note-on_87": 220, "note-on_88": 221, "note-on_89": 222, "note-on_90": 223, "note-on_91": 224, "note-on_92": 225, "note-on_93": 226, "note-on_94": 227, "note-on_95": 228, "note-on_96": 229, "note-on_97": 230, "note-on_98": 231, "note-on_99": 232, "note-on_100": 233, "note-on_101": 234, "note-on_102": 235, "note-on_103": 236, "note-on_104": 237, "note-on_105": 238, "note-on_106": 239, "note-on_107": 240, "note-on_108": 241, "note-on_109": 242, "note-on_110": 243, "note-on_111": 244, "note-on_112": 245, "note-on_113": 246, "note-on_114": 247, "note-on_115": 248, "note-on_116": 249, "note-on_117": 250, "note-on_118": 251, "note-on_119": 252, "note-on_120": 253, "note-on_121": 254, "note-on_122": 255, "note-on_123": 256, "note-on_124": 257, "note-on_125": 258, "note-on_126": 259, "note-on_127": 260, "note-off_0": 261, "note-off_1": 262, "note-off_2": 263, "note-off_3": 264, "note-off_4": 265, "note-off_5": 266, "note-off_6": 267, "note-off_7": 268, "note-off_8": 269, "note-off_9": 270, "note-off_10": 271, "note-off_11": 272, "note-off_12": 273, "note-off_13": 274, "note-off_14": 275, "note-off_15": 276, "note-off_16": 277, "note-off_17": 278, "note-off_18": 279, "note-off_19": 280, "note-off_20": 281, "note-off_21": 282, "note-off_22": 283, "note-off_23": 284, "note-off_24": 285, "note-off_25": 286, "note-off_26": 287, "note-off_27": 288, "note-off_28": 289, "note-off_29": 290, "note-off_30": 291, "note-off_31": 292, "note-off_32": 293, "note-off_33": 294, "note-off_34": 295, "note-off_35": 296, "note-off_36": 297, "note-off_37": 298, "note-off_38": 299, "note-off_39": 300, "note-off_40": 301, "note-off_41": 302, "note-off_42": 303, "note-off_43": 304, "note-off_44": 305, "note-off_45": 306, "note-off_46": 307, "note-off_47": 308, "note-off_48": 309, "note-off_49": 310, "note-off_50": 311, "note-off_51": 312, "note-off_52": 313, "note-off_53": 314, "note-off_54": 315, "note-off_55": 316, "note-off_56": 317, "note-off_57": 318, "note-off_58": 319, "note-off_59": 320, "note-off_60": 321, "note-off_61": 322, "note-off_62": 323, "note-off_63": 324, "note-off_64": 325, "note-off_65": 326, "note-off_66": 327, "note-off_67": 328, "note-off_68": 329, "note-off_69": 330, "note-off_70": 331, "note-off_71": 332, "note-off_72": 333, "note-off_73": 334, "note-off_74": 335, "note-off_75": 336, "note-off_76": 337, "note-off_77": 338, "note-off_78": 339, "note-off_79": 340, "note-off_80": 341, "note-off_81": 342, "note-off_82": 343, "note-off_83": 344, "note-off_84": 345, "note-off_85": 346, "note-off_86": 347, "note-off_87": 348, "note-off_88": 349, "note-off_89": 350, "note-off_90": 351, "note-off_91": 352, "note-off_92": 353, "note-off_93": 354, "note-off_94": 355, "note-off_95": 356, "note-off_96": 357, "note-off_97": 358, "note-off_98": 359, "note-off_99": 360, "note-off_100": 361, "note-off_101": 362, "note-off_102": 363, "note-off_103": 364, "note-off_104": 365, "note-off_105": 366, "note-off_106": 367, "note-off_107": 368, "note-off_108": 369, "note-off_109": 370, "note-off_110": 371, "note-off_111": 372, "note-off_112": 373, "note-off_113": 374, "note-off_114": 375, "note-off_115": 376, "note-off_116": 377, "note-off_117": 378, "note-off_118": 379, "note-off_119": 380, "note-off_120": 381, "note-off_121": 382, "note-off_122": 383, "note-off_123": 384, "note-off_124": 385, "note-off_125": 386, "note-off_126": 387, "note-off_127": 388, "time-shift_1": 389, "time-shift_2": 390, "time-shift_3": 391, "time-shift_4": 392, "time-shift_5": 393, "time-shift_6": 394, "time-shift_7": 395, "time-shift_8": 396, "time-shift_9": 397, "time-shift_10": 398, "time-shift_11": 399, "time-shift_12": 400, "time-shift_13": 401, "time-shift_14": 402, "time-shift_15": 403, "time-shift_16": 404, "time-shift_17": 405, "time-shift_18": 406, "time-shift_19": 407, "time-shift_20": 408, "time-shift_21": 409, "time-shift_22": 410, "time-shift_23": 411, "time-shift_24": 412, "time-shift_25": 413, "time-shift_26": 414, "time-shift_27": 415, "time-shift_28": 416, "time-shift_29": 417, "time-shift_30": 418, "time-shift_31": 419, "time-shift_32": 420, "time-shift_33": 421, "time-shift_34": 422, "time-shift_35": 423, "time-shift_36": 424, "time-shift_37": 425, "time-shift_38": 426, "time-shift_39": 427, "time-shift_40": 428, "time-shift_41": 429, "time-shift_42": 430, "time-shift_43": 431, "time-shift_44": 432, "time-shift_45": 433, "time-shift_46": 434, "time-shift_47": 435, "time-shift_48": 436}, "code_event_map": {"0": "start-of-song", "1": "end-of-song", "2": "start-of-bar", "3": "end-of-bar", "4": "start-of-track", "5": "end-of-track", "6": "instrument_grand-piano", "7": "instrument_bright-piano", "8": "instrument_electric-grand-piano", "9": "instrument_honky-tony-piano", "10": "instrument_electric-piano-1", "11": "instrument_electric-piano-2", "12": "instrument_harpsichord", "13": "instrument_clavinet", "14": "instrument_celesta", "15": "instrument_glockenspiel", "16": "instrument_music-box", "17": "instrument_vibraphone", "18": "instrument_marimba", "19": "instrument_xylophone", "20": "instrument_tubular-bells", "21": "instrument_dulcimer", "22": "instrument_dwawbar-organ", "23": "instrument_percussive-organ", "24": "instrument_rock-organ", "25": "instrument_church-organ", "26": "instrument_reed-organ", "27": "instrument_accordion", "28": "instrument_harmonica", "29": "instrument_bandoneon", "30": "instrument_nylon-string-guitar", "31": "instrument_steel-string-guitar", "32": "instrument_jazz-electric-guitar", "33": "instrument_clean-electric-guitar", "34": "instrument_muted-electric-guitar", "35": "instrument_overdriven-electric-guitar", "36": "instrument_distort-electric-guitar", "37": "instrument_guitar-harmonic", "38": "instrument_bass", "39": "instrument_finger-electric-bass", "40": "instrument_pick-electric-bass", "41": "instrument_fretless-electric-bass", "42": "instrument_slap-bass-1", "43": "instrument_slap-bass-2", "44": "instrument_synth-bass-1", "45": "instrument_synth-bass-2", "46": "instrument_violin", "47": "instrument_viola", "48": "instrument_cello", "49": "instrument_contrabass", "50": "instrument_tremelo-strings", "51": "instrument_pizzicato-strings", "52": "instrument_harp", "53": "instrument_timpani", "54": "instrument_strings", "55": "instrument_synth-strings-1", "56": "instrument_synth-strings-2", "57": "instrument_voices-aah", "58": "instrument_voices-ooh", "59": "instrument_synth-voice", "60": "instrument_orchestra-hit", "61": "instrument_trumpet", "62": "instrument_trombone", "63": "instrument_tuba", "64": "instrument_muted-trumpet", "65": "instrument_horn", "66": "instrument_brasses", "67": "instrument_synth-brasses-1", "68": "instrument_synth-brasses-2", "69": "instrument_soprano-saxophone", "70": "instrument_alto-saxophone", "71": "instrument_tenor-saxophone", "72": "instrument_baritone-saxophone", "73": "instrument_oboe", "74": "instrument_english-horn", "75": "instrument_bassoon", "76": "instrument_clarinet", "77": "instrument_piccolo", "78": "instrument_flute", "79": "instrument_recorder", "80": "instrument_pan-flute", "81": "instrument_blown-bottle", "82": "instrument_Shakuhachi", "83": "instrument_Whistle", "84": "instrument_ocarina", "85": "instrument_lead-square", "86": "instrument_lead-sawtooth", "87": "instrument_lead-calliope", "88": "instrument_lead-chiff", "89": "instrument_lead-charang", "90": "instrument_lead-voice", "91": "instrument_lead-fifths", "92": "instrument_lead-bass+lead", "93": "instrument_pad-new-age", "94": "instrument_pad-warm", "95": "instrument_pad-polysynth", "96": "instrument_pad-choir", "97": "instrument_pad-bowed", "98": "instrument_pad-metallic", "99": "instrument_pad-halo", "100": "instrument_pad-sweep", "101": "instrument_fx-rain", "102": "instrument_fx-soundtrack", "103": "instrument_fx-crystal", "104": "instrument_fx-atmosphere", "105": "instrument_fx-brightness", "106": "instrument_fx-goblins", "107": "instrument_fx-echoes", "108": "instrument_fx-scifi", "109": "instrument_sitar", "110": "instrument_banjo", "111": "instrument_shamisen", "112": "instrument_koto", "113": "instrument_kalimba", "114": "instrument_bag-pipe", "115": "instrument_shehnai", "116": "instrument_tinkle-bell", "117": "instrument_agogo", "118": "instrument_steel-drum", "119": "instrument_woodblock", "120": "instrument_taiko", "121": "instrument_melodic-tom", "122": "instrument_synth-drums", "123": "instrument_reverse-cymbal", "124": "instrument_guitar-fret-noise", "125": "instrument_breath-noise", "126": "instrument_seashore", "127": "instrument_bird-tweet", "128": "instrument_telephone-rang", "129": "instrument_helicopter", "130": "instrument_applause", "131": "instrument_gunshot", "132": "instrument_drumset", "133": "note-on_0", "134": "note-on_1", "135": "note-on_2", "136": "note-on_3", "137": "note-on_4", "138": "note-on_5", "139": "note-on_6", "140": "note-on_7", "141": "note-on_8", "142": "note-on_9", "143": "note-on_10", "144": "note-on_11", "145": "note-on_12", "146": "note-on_13", "147": "note-on_14", "148": "note-on_15", "149": "note-on_16", "150": "note-on_17", "151": "note-on_18", "152": "note-on_19", "153": "note-on_20", "154": "note-on_21", "155": "note-on_22", "156": "note-on_23", "157": "note-on_24", "158": "note-on_25", "159": "note-on_26", "160": "note-on_27", "161": "note-on_28", "162": "note-on_29", "163": "note-on_30", "164": "note-on_31", "165": "note-on_32", "166": "note-on_33", "167": "note-on_34", "168": "note-on_35", "169": "note-on_36", "170": "note-on_37", "171": "note-on_38", "172": "note-on_39", "173": "note-on_40", "174": "note-on_41", "175": "note-on_42", "176": "note-on_43", "177": "note-on_44", "178": "note-on_45", "179": "note-on_46", "180": "note-on_47", "181": "note-on_48", "182": "note-on_49", "183": "note-on_50", "184": "note-on_51", "185": "note-on_52", "186": "note-on_53", "187": "note-on_54", "188": "note-on_55", "189": "note-on_56", "190": "note-on_57", "191": "note-on_58", "192": "note-on_59", "193": "note-on_60", "194": "note-on_61", "195": "note-on_62", "196": "note-on_63", "197": "note-on_64", "198": "note-on_65", "199": "note-on_66", "200": "note-on_67", "201": "note-on_68", "202": "note-on_69", "203": "note-on_70", "204": "note-on_71", "205": "note-on_72", "206": "note-on_73", "207": "note-on_74", "208": "note-on_75", "209": "note-on_76", "210": "note-on_77", "211": "note-on_78", "212": "note-on_79", "213": "note-on_80", "214": "note-on_81", "215": "note-on_82", "216": "note-on_83", "217": "note-on_84", "218": "note-on_85", "219": "note-on_86", "220": "note-on_87", "221": "note-on_88", "222": "note-on_89", "223": "note-on_90", "224": "note-on_91", "225": "note-on_92", "226": "note-on_93", "227": "note-on_94", "228": "note-on_95", "229": "note-on_96", "230": "note-on_97", "231": "note-on_98", "232": "note-on_99", "233": "note-on_100", "234": "note-on_101", "235": "note-on_102", "236": "note-on_103", "237": "note-on_104", "238": "note-on_105", "239": "note-on_106", "240": "note-on_107", "241": "note-on_108", "242": "note-on_109", "243": "note-on_110", "244": "note-on_111", "245": "note-on_112", "246": "note-on_113", "247": "note-on_114", "248": "note-on_115", "249": "note-on_116", "250": "note-on_117", "251": "note-on_118", "252": "note-on_119", "253": "note-on_120", "254": "note-on_121", "255": "note-on_122", "256": "note-on_123", "257": "note-on_124", "258": "note-on_125", "259": "note-on_126", "260": "note-on_127", "261": "note-off_0", "262": "note-off_1", "263": "note-off_2", "264": "note-off_3", "265": "note-off_4", "266": "note-off_5", "267": "note-off_6", "268": "note-off_7", "269": "note-off_8", "270": "note-off_9", "271": "note-off_10", "272": "note-off_11", "273": "note-off_12", "274": "note-off_13", "275": "note-off_14", "276": "note-off_15", "277": "note-off_16", "278": "note-off_17", "279": "note-off_18", "280": "note-off_19", "281": "note-off_20", "282": "note-off_21", "283": "note-off_22", "284": "note-off_23", "285": "note-off_24", "286": "note-off_25", "287": "note-off_26", "288": "note-off_27", "289": "note-off_28", "290": "note-off_29", "291": "note-off_30", "292": "note-off_31", "293": "note-off_32", "294": "note-off_33", "295": "note-off_34", "296": "note-off_35", "297": "note-off_36", "298": "note-off_37", "299": "note-off_38", "300": "note-off_39", "301": "note-off_40", "302": "note-off_41", "303": "note-off_42", "304": "note-off_43", "305": "note-off_44", "306": "note-off_45", "307": "note-off_46", "308": "note-off_47", "309": "note-off_48", "310": "note-off_49", "311": "note-off_50", "312": "note-off_51", "313": "note-off_52", "314": "note-off_53", "315": "note-off_54", "316": "note-off_55", "317": "note-off_56", "318": "note-off_57", "319": "note-off_58", "320": "note-off_59", "321": "note-off_60", "322": "note-off_61", "323": "note-off_62", "324": "note-off_63", "325": "note-off_64", "326": "note-off_65", "327": "note-off_66", "328": "note-off_67", "329": "note-off_68", "330": "note-off_69", "331": "note-off_70", "332": "note-off_71", "333": "note-off_72", "334": "note-off_73", "335": "note-off_74", "336": "note-off_75", "337": "note-off_76", "338": "note-off_77", "339": "note-off_78", "340": "note-off_79", "341": "note-off_80", "342": "note-off_81", "343": "note-off_82", "344": "note-off_83", "345": "note-off_84", "346": "note-off_85", "347": "note-off_86", "348": "note-off_87", "349": "note-off_88", "350": "note-off_89", "351": "note-off_90", "352": "note-off_91", "353": "note-off_92", "354": "note-off_93", "355": "note-off_94", "356": "note-off_95", "357": "note-off_96", "358": "note-off_97", "359": "note-off_98", "360": "note-off_99", "361": "note-off_100", "362": "note-off_101", "363": "note-off_102", "364": "note-off_103", "365": "note-off_104", "366": "note-off_105", "367": "note-off_106", "368": "note-off_107", "369": "note-off_108", "370": "note-off_109", "371": "note-off_110", "372": "note-off_111", "373": "note-off_112", "374": "note-off_113", "375": "note-off_114", "376": "note-off_115", "377": "note-off_116", "378": "note-off_117", "379": "note-off_118", "380": "note-off_119", "381": "note-off_120", "382": "note-off_121", "383": "note-off_122", "384": "note-off_123", "385": "note-off_124", "386": "note-off_125", "387": "note-off_126", "388": "note-off_127", "389": "time-shift_1", "390": "time-shift_2", "391": "time-shift_3", "392": "time-shift_4", "393": "time-shift_5", "394": "time-shift_6", "395": "time-shift_7", "396": "time-shift_8", "397": "time-shift_9", "398": "time-shift_10", "399": "time-shift_11", "400": "time-shift_12", "401": "time-shift_13", "402": "time-shift_14", "403": "time-shift_15", "404": "time-shift_16", "405": "time-shift_17", "406": "time-shift_18", "407": "time-shift_19", "408": "time-shift_20", "409": "time-shift_21", "410": "time-shift_22", "411": "time-shift_23", "412": "time-shift_24", "413": "time-shift_25", "414": "time-shift_26", "415": "time-shift_27", "416": "time-shift_28", "417": "time-shift_29", "418": "time-shift_30", "419": "time-shift_31", "420": "time-shift_32", "421": "time-shift_33", "422": "time-shift_34", "423": "time-shift_35", "424": "time-shift_36", "425": "time-shift_37", "426": "time-shift_38", "427": "time-shift_39", "428": "time-shift_40", "429": "time-shift_41", "430": "time-shift_42", "431": "time-shift_43", "432": "time-shift_44", "433": "time-shift_45", "434": "time-shift_46", "435": "time-shift_47", "436": "time-shift_48"}}